AoikPDFBookmark-0.1.0.dist-info/DESCRIPTION.rst
AoikPDFBookmark-0.1.0.dist-info/METADATA
AoikPDFBookmark-0.1.0.dist-info/RECORD
AoikPDFBookmark-0.1.0.dist-info/WHEEL
AoikPDFBookmark-0.1.0.dist-info/entry_points.txt
AoikPDFBookmark-0.1.0.dist-info/metadata.json
AoikPDFBookmark-0.1.0.dist-info/top_level.txt
aoikpdfbookmark/__init__.py
aoikpdfbookmark/__main__.py
aoikpdfbookmark/aoikimportutil.py
aoikpdfbookmark/aoikpdfbookmark.py
aoikpdfbookmark/bookmark.py
aoikpdfbookmark/mediator.py
aoikpdfbookmark/pdfmaker.py
aoikpdfbookmark/pdfparser.py
